{"song":{"song":"Drink","player1":"bf","player2":"gf","needsVoices":false,"sectionLengths":[],"sections":68,"notes":[{"lengthInSteps":16,"bpm":161,"changeBPM":false,"mustHitSection":false,"typeOfSection":0,"sectionNotes":[]},{"lengthInSteps":16,"bpm":161,"changeBPM":false,"mustHitSection":false,"typeOfSection":0,"sectionNotes":[]},{"lengthInSteps":16,"bpm":161,"changeBPM":false,"mustHitSection":true,"typeOfSection":0,"sectionNotes":[[1091,1,0],[1278,1,0],[1931,3,0],[2024,3,0],[2117,3,0]]},{"lengthInSteps":16,"bpm":161,"changeBPM":false,"mustHitSection":false,"typeOfSection":0,"sectionNotes":[[2677,2,0],[2864,2,0],[3237,1,0],[3330,1,0],[3424,1,0],[3610,1,0]]},{"lengthInSteps":16,"bpm":161,"changeBPM":false,"mustHitSection":true,"typeOfSection":0,"sectionNotes":[[4170,1,0],[4356,1,0],[4916,0,0],[5010,0,0],[5103,0,0],[5663,1,373],[6222,0,373]]},{"lengthInSteps":16,"bpm":161,"changeBPM":false,"mustHitSection":false,"typeOfSection":0,"sectionNotes":[[7062,0,0],[7249,0,0],[7435,1,559]]},{"lengthInSteps":16,"bpm":161,"changeBPM":false,"mustHitSection":true,"typeOfSection":0,"sectionNotes":[[8648,3,0],[8835,3,0],[9021,3,466],[9674,1,466]]},{"lengthInSteps":16,"bpm":161,"changeBPM":false,"mustHitSection":false,"typeOfSection":0,"sectionNotes":[[10514,2,0],[10887,2,0],[10980,2,0],[11074,3,186]]},{"lengthInSteps":16,"bpm":161,"changeBPM":false,"mustHitSection":true,"typeOfSection":0,"sectionNotes":[[11633,3,0],[11727,3,0],[12007,3,466],[12753,1,466]]},{"lengthInSteps":16,"bpm":161,"changeBPM":false,"mustHitSection":false,"typeOfSection":0,"sectionNotes":[[13593,1,0],[13873,1,0],[13966,1,0],[14059,1,0],[14246,0,279],[14619,0,0],[14806,0,0]]},{"lengthInSteps":16,"bpm":161,"changeBPM":false,"mustHitSection":true,"typeOfSection":0,"sectionNotes":[[14992,0,0],[15179,0,746]]},{"lengthInSteps":16,"bpm":161,"changeBPM":false,"mustHitSection":false,"typeOfSection":0,"sectionNotes":[[16205,0,0],[16298,0,0],[16485,0,93],[16858,1,0],[16951,1,0],[17045,1,0],[17231,1,373]]},{"lengthInSteps":16,"bpm":161,"changeBPM":false,"mustHitSection":true,"typeOfSection":0,"sectionNotes":[[18817,1,0],[19190,1,279]]},{"lengthInSteps":16,"bpm":161,"changeBPM":false,"mustHitSection":false,"typeOfSection":0,"sectionNotes":[[19750,2,0],[19843,2,559]]},{"lengthInSteps":16,"bpm":161,"changeBPM":false,"mustHitSection":true,"typeOfSection":0,"sectionNotes":[[20683,0,0],[20776,0,1119]]},{"lengthInSteps":16,"bpm":161,"changeBPM":false,"mustHitSection":false,"typeOfSection":0,"sectionNotes":[[22176,0,0],[22362,0,0],[22549,0,0],[22736,0,0],[22922,0,373]]},{"lengthInSteps":16,"bpm":161,"changeBPM":false,"mustHitSection":true,"typeOfSection":0,"sectionNotes":[[23669,1,0],[23855,1,0],[24042,1,279],[24415,2,0],[24508,2,0],[24602,2,0],[24695,2,559]]},{"lengthInSteps":16,"bpm":161,"changeBPM":false,"mustHitSection":false,"typeOfSection":0,"sectionNotes":[[25534,3,0],[25721,3,0],[25908,3,0],[26094,2,0],[26188,2,373],[26654,2,0],[26841,2,0],[27027,2,0],[27214,1,559]]},{"lengthInSteps":16,"bpm":161,"changeBPM":false,"mustHitSection":true,"typeOfSection":0,"sectionNotes":[[28147,0,1865],[30199,1,0],[30386,1,0],[30479,1,0],[30572,1,0],[30759,0,0]]},{"lengthInSteps":16,"bpm":161,"changeBPM":false,"mustHitSection":false,"typeOfSection":0,"sectionNotes":[[31132,0,0],[31319,1,0],[31505,1,0],[31692,3,373]]},{"lengthInSteps":16,"bpm":161,"changeBPM":false,"mustHitSection":true,"typeOfSection":0,"sectionNotes":[[32438,2,0],[32625,2,0],[32998,1,0],[33185,1,0],[33371,1,0]]},{"lengthInSteps":16,"bpm":161,"changeBPM":false,"mustHitSection":false,"typeOfSection":0,"sectionNotes":[[33744,1,186],[34118,0,186],[34491,0,186],[34864,0,186],[35237,0,932],[36357,2,0]]},{"lengthInSteps":16,"bpm":161,"changeBPM":false,"mustHitSection":true,"typeOfSection":0,"sectionNotes":[[37010,3,0],[37103,3,0],[37476,3,0],[37663,3,0],[37849,3,0],[38223,2,373],[38969,2,373]]},{"lengthInSteps":16,"bpm":161,"changeBPM":false,"mustHitSection":false,"typeOfSection":0,"sectionNotes":[[39809,1,0],[39995,1,0],[40089,0,0],[40462,0,0],[40648,0,0],[40928,0,559],[41581,1,0],[42048,1,0],[42141,1,0]]},{"lengthInSteps":16,"bpm":161,"changeBPM":false,"mustHitSection":true,"typeOfSection":0,"sectionNotes":[[42514,3,0],[42701,3,0],[42887,3,0],[43074,3,0],[43540,2,932],[44567,2,0],[44753,2,0],[44847,2,0],[45220,2,0],[45406,2,0]]},{"lengthInSteps":16,"bpm":161,"changeBPM":false,"mustHitSection":false,"typeOfSection":0,"sectionNotes":[[45780,1,0],[45966,0,0],[46153,0,0],[46339,0,0],[46526,0,0],[46712,0,0],[46899,0,932],[48112,0,0],[48392,1,0]]},{"lengthInSteps":16,"bpm":161,"changeBPM":false,"mustHitSection":true,"typeOfSection":0,"sectionNotes":[[48952,2,279],[49511,3,279],[49885,2,279],[50258,1,0],[50444,1,0],[50631,1,279],[51004,2,559]]},{"lengthInSteps":16,"bpm":161,"changeBPM":false,"mustHitSection":false,"typeOfSection":0,"sectionNotes":[[52124,3,279],[52497,3,0],[52683,3,0],[52870,3,186],[53150,3,0],[53430,3,0],[53616,3,0],[54083,2,0],[54363,1,0]]},{"lengthInSteps":16,"bpm":161,"changeBPM":false,"mustHitSection":true,"typeOfSection":0,"sectionNotes":[[55202,1,1119],[56508,3,0],[56695,3,0],[56975,3,0],[57348,2,373]]},{"lengthInSteps":16,"bpm":161,"changeBPM":false,"mustHitSection":false,"typeOfSection":0,"sectionNotes":[[58001,0,0],[58188,0,0],[58374,0,559],[59307,0,0],[59494,0,0],[59681,0,0],[59867,0,559]]},{"lengthInSteps":16,"bpm":161,"changeBPM":false,"mustHitSection":true,"typeOfSection":0,"sectionNotes":[[60987,1,0],[61173,1,0],[61360,2,186],[61733,2,186],[62106,1,186],[62479,0,186],[62853,0,186],[63226,0,373]]},{"lengthInSteps":16,"bpm":161,"changeBPM":false,"mustHitSection":false,"typeOfSection":0,"sectionNotes":[[63972,1,0],[64159,1,0],[64345,2,0],[64532,2,0],[64718,2,932],[66025,2,0],[66398,2,0]]},{"lengthInSteps":16,"bpm":161,"changeBPM":false,"mustHitSection":true,"typeOfSection":0,"sectionNotes":[[67144,3,0],[67517,3,0],[67704,3,373],[68450,3,0],[68544,3,0],[68637,3,0],[69010,2,0],[69197,2,0],[69383,2,0]]},{"lengthInSteps":16,"bpm":161,"changeBPM":false,"mustHitSection":false,"typeOfSection":0,"sectionNotes":[[69943,0,0],[70036,0,0],[70130,0,839],[71249,1,0],[71436,1,0],[71622,1,0],[71995,2,0],[72182,3,0],[72369,3,0]]},{"lengthInSteps":16,"bpm":161,"changeBPM":false,"mustHitSection":true,"typeOfSection":0,"sectionNotes":[[72928,0,1119],[74421,0,0],[74608,1,0],[74981,1,0],[75354,1,0]]},{"lengthInSteps":16,"bpm":161,"changeBPM":false,"mustHitSection":false,"typeOfSection":0,"sectionNotes":[[75914,2,0],[76100,2,0],[76287,2,0],[76474,2,0],[76660,2,0],[76847,2,0],[77220,1,0],[77407,1,0],[77593,1,0],[77780,1,0],[77966,1,559]]},{"lengthInSteps":16,"bpm":161,"changeBPM":false,"mustHitSection":true,"typeOfSection":0,"sectionNotes":[[79459,0,186],[79926,2,0],[80019,2,186],[80765,2,0],[80859,2,186],[81418,2,0],[81512,2,186]]},{"lengthInSteps":16,"bpm":161,"changeBPM":false,"mustHitSection":false,"typeOfSection":0,"sectionNotes":[[82538,1,0],[82911,0,0],[83004,0,0],[83098,0,0]]},{"lengthInSteps":16,"bpm":161,"changeBPM":false,"mustHitSection":true,"typeOfSection":0,"sectionNotes":[[83284,0,0],[83657,0,0],[83751,0,0],[83844,0,0]]},{"lengthInSteps":16,"bpm":161,"changeBPM":false,"mustHitSection":false,"typeOfSection":0,"sectionNotes":[[84031,0,466],[84777,1,559],[85523,2,0],[85896,3,0],[85990,3,0],[86176,3,0]]},{"lengthInSteps":16,"bpm":161,"changeBPM":false,"mustHitSection":true,"typeOfSection":0,"sectionNotes":[[87016,0,279],[87762,0,279],[88136,1,0],[88322,2,0]]},{"lengthInSteps":16,"bpm":161,"changeBPM":false,"mustHitSection":false,"typeOfSection":0,"sectionNotes":[[88509,3,0],[88882,3,0],[88975,3,0],[89069,3,0],[89255,2,559]]},{"lengthInSteps":16,"bpm":161,"changeBPM":false,"mustHitSection":true,"typeOfSection":0,"sectionNotes":[[90001,1,0],[90188,0,0],[90281,0,0],[90375,0,0],[90561,0,0]]},{"lengthInSteps":16,"bpm":161,"changeBPM":false,"mustHitSection":false,"typeOfSection":0,"sectionNotes":[[102876,3,0],[103156,3,186],[103529,3,0],[103716,3,0],[103902,3,373],[104462,1,0],[104649,1,0],[104835,1,0]]},{"lengthInSteps":16,"bpm":161,"changeBPM":false,"mustHitSection":true,"typeOfSection":0,"sectionNotes":[[105395,1,186],[105768,0,0],[105955,0,0],[106142,0,279],[106515,2,0],[106888,2,0],[107261,2,0],[107448,2,0],[107634,2,186],[108007,3,0],[108101,3,0],[108194,3,0]]},{"lengthInSteps":16,"bpm":161,"changeBPM":false,"mustHitSection":false,"typeOfSection":0,"sectionNotes":[[108940,3,0],[109127,3,0],[109220,3,0],[109500,3,0],[109593,2,279],[110247,1,279],[110620,0,0],[110900,0,0],[111086,0,0]]},{"lengthInSteps":16,"bpm":161,"changeBPM":false,"mustHitSection":true,"typeOfSection":0,"sectionNotes":[[111273,0,279],[111739,2,279],[112112,3,279],[112672,1,0],[112859,1,0],[113045,0,0],[113232,0,0]]},{"lengthInSteps":16,"bpm":161,"changeBPM":false,"mustHitSection":false,"typeOfSection":0,"sectionNotes":[[115098,0,186],[115471,1,186],[115844,0,186],[116217,1,0],[116404,2,0],[116591,3,279],[117150,2,0],[117337,2,279]]},{"lengthInSteps":16,"bpm":161,"changeBPM":false,"mustHitSection":true,"typeOfSection":0,"sectionNotes":[[117803,1,0],[117897,1,0],[118083,1,559],[119016,0,0],[119203,0,186],[119576,0,559]]},{"lengthInSteps":16,"bpm":161,"changeBPM":false,"mustHitSection":false,"typeOfSection":0,"sectionNotes":[[121069,0,0],[121255,0,0],[121442,1,0],[121629,1,559],[122561,2,653]]},{"lengthInSteps":16,"bpm":161,"changeBPM":false,"mustHitSection":true,"typeOfSection":0,"sectionNotes":[[123681,0,0],[124054,0,0],[124241,0,0],[124427,1,373],[125174,2,0],[125360,2,0],[125454,2,0],[125640,2,932]]},{"lengthInSteps":16,"bpm":161,"changeBPM":false,"mustHitSection":false,"typeOfSection":0,"sectionNotes":[[127133,3,279],[127506,2,279],[127879,3,186],[128439,2,0],[128626,2,0],[128999,2,0],[129372,2,0]]},{"lengthInSteps":16,"bpm":161,"changeBPM":false,"mustHitSection":true,"typeOfSection":0,"sectionNotes":[[129932,1,559],[130865,0,0],[131238,0,0],[131425,0,0],[131611,0,186],[131984,1,0],[132171,1,0],[132357,1,0]]},{"lengthInSteps":16,"bpm":161,"changeBPM":false,"mustHitSection":false,"typeOfSection":0,"sectionNotes":[[132917,0,279],[133477,0,279],[133850,1,0],[134503,2,0],[134690,2,0],[134970,3,0],[135343,3,0]]},{"lengthInSteps":16,"bpm":161,"changeBPM":false,"mustHitSection":true,"typeOfSection":0,"sectionNotes":[[135996,3,186],[136462,1,186],[136836,1,186],[137209,1,186],[137582,0,559],[138328,0,93]]},{"lengthInSteps":16,"bpm":161,"changeBPM":false,"mustHitSection":false,"typeOfSection":0,"sectionNotes":[[139168,3,1119],[140474,3,279],[140941,2,279],[141407,1,279],[141874,3,0],[142060,3,0],[142340,3,746],[143273,1,0],[143460,1,0],[143646,1,0],[144019,0,559]]},{"lengthInSteps":16,"bpm":161,"changeBPM":false,"mustHitSection":true,"typeOfSection":0,"sectionNotes":[[144952,3,0],[145139,3,186],[145512,3,0],[145885,2,0],[146445,1,0],[146632,1,0],[147005,0,559],[147938,0,0],[148124,0,0],[148498,1,559],[149244,3,0],[149617,3,559],[150363,3,0]]},{"lengthInSteps":16,"bpm":161,"changeBPM":false,"mustHitSection":false,"typeOfSection":0,"sectionNotes":[[151203,0,746],[152509,2,373],[153069,3,0],[153442,3,186],[154002,3,0],[154189,3,0],[154468,3,186],[154842,1,186],[155308,1,373],[156054,2,279]]},{"lengthInSteps":16,"bpm":161,"changeBPM":false,"mustHitSection":true,"typeOfSection":0,"sectionNotes":[[156987,0,559],[157920,0,186],[158480,0,0],[158667,0,186],[159040,1,186],[159413,2,186],[159973,2,0],[160159,2,0],[160533,3,932],[161652,3,0],[162025,3,0],[162399,3,0]]},{"lengthInSteps":16,"bpm":161,"changeBPM":false,"mustHitSection":false,"typeOfSection":0,"sectionNotes":[[163052,0,932],[164451,0,0],[164638,0,279],[165011,1,0],[165384,2,0],[165944,3,0],[166130,3,186],[166504,3,186],[166877,1,186],[167250,1,373],[167996,2,0],[168183,2,0],[168369,2,0]]},{"lengthInSteps":16,"bpm":161,"changeBPM":false,"mustHitSection":true,"typeOfSection":0,"sectionNotes":[[168929,0,373],[169489,0,559],[170422,1,0],[170608,1,0],[170982,2,0],[171355,3,186],[171915,3,279],[172568,1,279],[172941,1,0],[173221,1,559],[173967,2,0],[174340,2,0]]},{"lengthInSteps":16,"bpm":161,"changeBPM":false,"mustHitSection":false,"typeOfSection":0,"sectionNotes":[[175087,3,0],[175273,3,0],[175460,3,0],[175646,3,0],[175833,3,0],[176393,2,466],[177046,2,93],[177326,2,93]]},{"lengthInSteps":16,"bpm":161,"changeBPM":false,"mustHitSection":true,"typeOfSection":0,"sectionNotes":[[177886,2,279],[178539,1,93],[178818,0,279],[179285,0,186],[179658,0,0],[179938,1,0],[180125,1,0],[180311,1,0]]},{"lengthInSteps":16,"bpm":161,"changeBPM":false,"mustHitSection":false,"typeOfSection":0,"sectionNotes":[[180964,2,186],[181431,2,0],[181524,2,559],[182457,1,0],[182644,1,186],[183017,1,186],[183390,2,0],[183670,2,5485]]},{"lengthInSteps":16,"bpm":161,"changeBPM":false,"mustHitSection":true,"typeOfSection":0,"sectionNotes":[[187215,3,0],[187402,3,0],[187588,3,186],[188241,3,1492],[189921,3,0],[190107,3,0],[190294,3,0]]},{"lengthInSteps":16,"bpm":161,"changeBPM":false,"mustHitSection":false,"typeOfSection":0,"sectionNotes":[[190480,2,186],[190947,1,0],[191040,1,0],[191227,1,186],[191787,0,0],[191880,0,0],[191973,0,279]]},{"lengthInSteps":16,"bpm":161,"changeBPM":false,"mustHitSection":true,"typeOfSection":0,"sectionNotes":[[192719,0,186],[193186,2,0],[193279,2,0],[193466,2,186],[193839,3,0],[193932,3,0],[194026,3,0],[194212,3,279]]},{"lengthInSteps":16,"bpm":161,"changeBPM":false,"mustHitSection":false,"typeOfSection":0,"sectionNotes":[[194679,1,0],[194865,1,0],[195052,1,93],[195238,0,0],[195332,0,0],[195425,0,0],[195612,0,373]]},{"lengthInSteps":16,"bpm":161,"changeBPM":false,"mustHitSection":true,"typeOfSection":0,"sectionNotes":[[196171,2,559],[196918,2,0],[197011,2,0],[197104,2,0],[197291,3,186],[197571,3,466]]}],"bpm":161,"speed":1},"notes":[{"lengthInSteps":16,"bpm":161,"changeBPM":false,"mustHitSection":false,"typeOfSection":0,"sectionNotes":[]},{"lengthInSteps":16,"bpm":161,"changeBPM":false,"mustHitSection":false,"typeOfSection":0,"sectionNotes":[]},{"lengthInSteps":16,"bpm":161,"changeBPM":false,"mustHitSection":true,"typeOfSection":0,"sectionNotes":[[1091,1,0],[1278,1,0],[1931,3,0],[2024,3,0],[2117,3,0]]},{"lengthInSteps":16,"bpm":161,"changeBPM":false,"mustHitSection":false,"typeOfSection":0,"sectionNotes":[[2677,2,0],[2864,2,0],[3237,1,0],[3330,1,0],[3424,1,0],[3610,1,0]]},{"lengthInSteps":16,"bpm":161,"changeBPM":false,"mustHitSection":true,"typeOfSection":0,"sectionNotes":[[4170,1,0],[4356,1,0],[4916,0,0],[5010,0,0],[5103,0,0],[5663,1,373],[6222,0,373]]},{"lengthInSteps":16,"bpm":161,"changeBPM":false,"mustHitSection":false,"typeOfSection":0,"sectionNotes":[[7062,0,0],[7249,0,0],[7435,1,559]]},{"lengthInSteps":16,"bpm":161,"changeBPM":false,"mustHitSection":true,"typeOfSection":0,"sectionNotes":[[8648,3,0],[8835,3,0],[9021,3,466],[9674,1,466]]},{"lengthInSteps":16,"bpm":161,"changeBPM":false,"mustHitSection":false,"typeOfSection":0,"sectionNotes":[[10514,2,0],[10887,2,0],[10980,2,0],[11074,3,186]]},{"lengthInSteps":16,"bpm":161,"changeBPM":false,"mustHitSection":true,"typeOfSection":0,"sectionNotes":[[11633,3,0],[11727,3,0],[12007,3,466],[12753,1,466]]},{"lengthInSteps":16,"bpm":161,"changeBPM":false,"mustHitSection":false,"typeOfSection":0,"sectionNotes":[[13593,1,0],[13873,1,0],[13966,1,0],[14059,1,0],[14246,0,279],[14619,0,0],[14806,0,0]]},{"lengthInSteps":16,"bpm":161,"changeBPM":false,"mustHitSection":true,"typeOfSection":0,"sectionNotes":[[14992,0,0],[15179,0,746]]},{"lengthInSteps":16,"bpm":161,"changeBPM":false,"mustHitSection":false,"typeOfSection":0,"sectionNotes":[[16205,0,0],[16298,0,0],[16485,0,93],[16858,1,0],[16951,1,0],[17045,1,0],[17231,1,373]]},{"lengthInSteps":16,"bpm":161,"changeBPM":false,"mustHitSection":true,"typeOfSection":0,"sectionNotes":[[18817,1,0],[19190,1,279]]},{"lengthInSteps":16,"bpm":161,"changeBPM":false,"mustHitSection":false,"typeOfSection":0,"sectionNotes":[[19750,2,0],[19843,2,559]]},{"lengthInSteps":16,"bpm":161,"changeBPM":false,"mustHitSection":true,"typeOfSection":0,"sectionNotes":[[20683,0,0],[20776,0,1119]]},{"lengthInSteps":16,"bpm":161,"changeBPM":false,"mustHitSection":false,"typeOfSection":0,"sectionNotes":[[22176,0,0],[22362,0,0],[22549,0,0],[22736,0,0],[22922,0,373]]},{"lengthInSteps":16,"bpm":161,"changeBPM":false,"mustHitSection":true,"typeOfSection":0,"sectionNotes":[[23669,1,0],[23855,1,0],[24042,1,279],[24415,2,0],[24508,2,0],[24602,2,0],[24695,2,559]]},{"lengthInSteps":16,"bpm":161,"changeBPM":false,"mustHitSection":false,"typeOfSection":0,"sectionNotes":[[25534,3,0],[25721,3,0],[25908,3,0],[26094,2,0],[26188,2,373],[26654,2,0],[26841,2,0],[27027,2,0],[27214,1,559]]},{"lengthInSteps":16,"bpm":161,"changeBPM":false,"mustHitSection":true,"typeOfSection":0,"sectionNotes":[[28147,0,1865],[30199,1,0],[30386,1,0],[30479,1,0],[30572,1,0],[30759,0,0]]},{"lengthInSteps":16,"bpm":161,"changeBPM":false,"mustHitSection":false,"typeOfSection":0,"sectionNotes":[[31132,0,0],[31319,1,0],[31505,1,0],[31692,3,373]]},{"lengthInSteps":16,"bpm":161,"changeBPM":false,"mustHitSection":true,"typeOfSection":0,"sectionNotes":[[32438,2,0],[32625,2,0],[32998,1,0],[33185,1,0],[33371,1,0]]},{"lengthInSteps":16,"bpm":161,"changeBPM":false,"mustHitSection":false,"typeOfSection":0,"sectionNotes":[[33744,1,186],[34118,0,186],[34491,0,186],[34864,0,186],[35237,0,932],[36357,2,0]]},{"lengthInSteps":16,"bpm":161,"changeBPM":false,"mustHitSection":true,"typeOfSection":0,"sectionNotes":[[37010,3,0],[37103,3,0],[37476,3,0],[37663,3,0],[37849,3,0],[38223,2,373],[38969,2,373]]},{"lengthInSteps":16,"bpm":161,"changeBPM":false,"mustHitSection":false,"typeOfSection":0,"sectionNotes":[[39809,1,0],[39995,1,0],[40089,0,0],[40462,0,0],[40648,0,0],[40928,0,559],[41581,1,0],[42048,1,0],[42141,1,0]]},{"lengthInSteps":16,"bpm":161,"changeBPM":false,"mustHitSection":true,"typeOfSection":0,"sectionNotes":[[42514,3,0],[42701,3,0],[42887,3,0],[43074,3,0],[43540,2,932],[44567,2,0],[44753,2,0],[44847,2,0],[45220,2,0],[45406,2,0]]},{"lengthInSteps":16,"bpm":161,"changeBPM":false,"mustHitSection":false,"typeOfSection":0,"sectionNotes":[[45780,1,0],[45966,0,0],[46153,0,0],[46339,0,0],[46526,0,0],[46712,0,0],[46899,0,932],[48112,0,0],[48392,1,0]]},{"lengthInSteps":16,"bpm":161,"changeBPM":false,"mustHitSection":true,"typeOfSection":0,"sectionNotes":[[48952,2,279],[49511,3,279],[49885,2,279],[50258,1,0],[50444,1,0],[50631,1,279],[51004,2,559]]},{"lengthInSteps":16,"bpm":161,"changeBPM":false,"mustHitSection":false,"typeOfSection":0,"sectionNotes":[[52124,3,279],[52497,3,0],[52683,3,0],[52870,3,186],[53150,3,0],[53430,3,0],[53616,3,0],[54083,2,0],[54363,1,0]]},{"lengthInSteps":16,"bpm":161,"changeBPM":false,"mustHitSection":true,"typeOfSection":0,"sectionNotes":[[55202,1,1119],[56508,3,0],[56695,3,0],[56975,3,0],[57348,2,373]]},{"lengthInSteps":16,"bpm":161,"changeBPM":false,"mustHitSection":false,"typeOfSection":0,"sectionNotes":[[58001,0,0],[58188,0,0],[58374,0,559],[59307,0,0],[59494,0,0],[59681,0,0],[59867,0,559]]},{"lengthInSteps":16,"bpm":161,"changeBPM":false,"mustHitSection":true,"typeOfSection":0,"sectionNotes":[[60987,1,0],[61173,1,0],[61360,2,186],[61733,2,186],[62106,1,186],[62479,0,186],[62853,0,186],[63226,0,373]]},{"lengthInSteps":16,"bpm":161,"changeBPM":false,"mustHitSection":false,"typeOfSection":0,"sectionNotes":[[63972,1,0],[64159,1,0],[64345,2,0],[64532,2,0],[64718,2,932],[66025,2,0],[66398,2,0]]},{"lengthInSteps":16,"bpm":161,"changeBPM":false,"mustHitSection":true,"typeOfSection":0,"sectionNotes":[[67144,3,0],[67517,3,0],[67704,3,373],[68450,3,0],[68544,3,0],[68637,3,0],[69010,2,0],[69197,2,0],[69383,2,0]]},{"lengthInSteps":16,"bpm":161,"changeBPM":false,"mustHitSection":false,"typeOfSection":0,"sectionNotes":[[69943,0,0],[70036,0,0],[70130,0,839],[71249,1,0],[71436,1,0],[71622,1,0],[71995,2,0],[72182,3,0],[72369,3,0]]},{"lengthInSteps":16,"bpm":161,"changeBPM":false,"mustHitSection":true,"typeOfSection":0,"sectionNotes":[[72928,0,1119],[74421,0,0],[74608,1,0],[74981,1,0],[75354,1,0]]},{"lengthInSteps":16,"bpm":161,"changeBPM":false,"mustHitSection":false,"typeOfSection":0,"sectionNotes":[[75914,2,0],[76100,2,0],[76287,2,0],[76474,2,0],[76660,2,0],[76847,2,0],[77220,1,0],[77407,1,0],[77593,1,0],[77780,1,0],[77966,1,559]]},{"lengthInSteps":16,"bpm":161,"changeBPM":false,"mustHitSection":true,"typeOfSection":0,"sectionNotes":[[79459,0,186],[79926,2,0],[80019,2,186],[80765,2,0],[80859,2,186],[81418,2,0],[81512,2,186]]},{"lengthInSteps":16,"bpm":161,"changeBPM":false,"mustHitSection":false,"typeOfSection":0,"sectionNotes":[[82538,1,0],[82911,0,0],[83004,0,0],[83098,0,0]]},{"lengthInSteps":16,"bpm":161,"changeBPM":false,"mustHitSection":true,"typeOfSection":0,"sectionNotes":[[83284,0,0],[83657,0,0],[83751,0,0],[83844,0,0]]},{"lengthInSteps":16,"bpm":161,"changeBPM":false,"mustHitSection":false,"typeOfSection":0,"sectionNotes":[[84031,0,466],[84777,1,559],[85523,2,0],[85896,3,0],[85990,3,0],[86176,3,0]]},{"lengthInSteps":16,"bpm":161,"changeBPM":false,"mustHitSection":true,"typeOfSection":0,"sectionNotes":[[87016,0,279],[87762,0,279],[88136,1,0],[88322,2,0]]},{"lengthInSteps":16,"bpm":161,"changeBPM":false,"mustHitSection":false,"typeOfSection":0,"sectionNotes":[[88509,3,0],[88882,3,0],[88975,3,0],[89069,3,0],[89255,2,559]]},{"lengthInSteps":16,"bpm":161,"changeBPM":false,"mustHitSection":true,"typeOfSection":0,"sectionNotes":[[90001,1,0],[90188,0,0],[90281,0,0],[90375,0,0],[90561,0,0]]},{"lengthInSteps":16,"bpm":161,"changeBPM":false,"mustHitSection":false,"typeOfSection":0,"sectionNotes":[[102876,3,0],[103156,3,186],[103529,3,0],[103716,3,0],[103902,3,373],[104462,1,0],[104649,1,0],[104835,1,0]]},{"lengthInSteps":16,"bpm":161,"changeBPM":false,"mustHitSection":true,"typeOfSection":0,"sectionNotes":[[105395,1,186],[105768,0,0],[105955,0,0],[106142,0,279],[106515,2,0],[106888,2,0],[107261,2,0],[107448,2,0],[107634,2,186],[108007,3,0],[108101,3,0],[108194,3,0]]},{"lengthInSteps":16,"bpm":161,"changeBPM":false,"mustHitSection":false,"typeOfSection":0,"sectionNotes":[[108940,3,0],[109127,3,0],[109220,3,0],[109500,3,0],[109593,2,279],[110247,1,279],[110620,0,0],[110900,0,0],[111086,0,0]]},{"lengthInSteps":16,"bpm":161,"changeBPM":false,"mustHitSection":true,"typeOfSection":0,"sectionNotes":[[111273,0,279],[111739,2,279],[112112,3,279],[112672,1,0],[112859,1,0],[113045,0,0],[113232,0,0]]},{"lengthInSteps":16,"bpm":161,"changeBPM":false,"mustHitSection":false,"typeOfSection":0,"sectionNotes":[[115098,0,186],[115471,1,186],[115844,0,186],[116217,1,0],[116404,2,0],[116591,3,279],[117150,2,0],[117337,2,279]]},{"lengthInSteps":16,"bpm":161,"changeBPM":false,"mustHitSection":true,"typeOfSection":0,"sectionNotes":[[117803,1,0],[117897,1,0],[118083,1,559],[119016,0,0],[119203,0,186],[119576,0,559]]},{"lengthInSteps":16,"bpm":161,"changeBPM":false,"mustHitSection":false,"typeOfSection":0,"sectionNotes":[[121069,0,0],[121255,0,0],[121442,1,0],[121629,1,559],[122561,2,653]]},{"lengthInSteps":16,"bpm":161,"changeBPM":false,"mustHitSection":true,"typeOfSection":0,"sectionNotes":[[123681,0,0],[124054,0,0],[124241,0,0],[124427,1,373],[125174,2,0],[125360,2,0],[125454,2,0],[125640,2,932]]},{"lengthInSteps":16,"bpm":161,"changeBPM":false,"mustHitSection":false,"typeOfSection":0,"sectionNotes":[[127133,3,279],[127506,2,279],[127879,3,186],[128439,2,0],[128626,2,0],[128999,2,0],[129372,2,0]]},{"lengthInSteps":16,"bpm":161,"changeBPM":false,"mustHitSection":true,"typeOfSection":0,"sectionNotes":[[129932,1,559],[130865,0,0],[131238,0,0],[131425,0,0],[131611,0,186],[131984,1,0],[132171,1,0],[132357,1,0]]},{"lengthInSteps":16,"bpm":161,"changeBPM":false,"mustHitSection":false,"typeOfSection":0,"sectionNotes":[[132917,0,279],[133477,0,279],[133850,1,0],[134503,2,0],[134690,2,0],[134970,3,0],[135343,3,0]]},{"lengthInSteps":16,"bpm":161,"changeBPM":false,"mustHitSection":true,"typeOfSection":0,"sectionNotes":[[135996,3,186],[136462,1,186],[136836,1,186],[137209,1,186],[137582,0,559],[138328,0,93]]},{"lengthInSteps":16,"bpm":161,"changeBPM":false,"mustHitSection":false,"typeOfSection":0,"sectionNotes":[[139168,3,1119],[140474,3,279],[140941,2,279],[141407,1,279],[141874,3,0],[142060,3,0],[142340,3,746],[143273,1,0],[143460,1,0],[143646,1,0],[144019,0,559]]},{"lengthInSteps":16,"bpm":161,"changeBPM":false,"mustHitSection":true,"typeOfSection":0,"sectionNotes":[[144952,3,0],[145139,3,186],[145512,3,0],[145885,2,0],[146445,1,0],[146632,1,0],[147005,0,559],[147938,0,0],[148124,0,0],[148498,1,559],[149244,3,0],[149617,3,559],[150363,3,0]]},{"lengthInSteps":16,"bpm":161,"changeBPM":false,"mustHitSection":false,"typeOfSection":0,"sectionNotes":[[151203,0,746],[152509,2,373],[153069,3,0],[153442,3,186],[154002,3,0],[154189,3,0],[154468,3,186],[154842,1,186],[155308,1,373],[156054,2,279]]},{"lengthInSteps":16,"bpm":161,"changeBPM":false,"mustHitSection":true,"typeOfSection":0,"sectionNotes":[[156987,0,559],[157920,0,186],[158480,0,0],[158667,0,186],[159040,1,186],[159413,2,186],[159973,2,0],[160159,2,0],[160533,3,932],[161652,3,0],[162025,3,0],[162399,3,0]]},{"lengthInSteps":16,"bpm":161,"changeBPM":false,"mustHitSection":false,"typeOfSection":0,"sectionNotes":[[163052,0,932],[164451,0,0],[164638,0,279],[165011,1,0],[165384,2,0],[165944,3,0],[166130,3,186],[166504,3,186],[166877,1,186],[167250,1,373],[167996,2,0],[168183,2,0],[168369,2,0]]},{"lengthInSteps":16,"bpm":161,"changeBPM":false,"mustHitSection":true,"typeOfSection":0,"sectionNotes":[[168929,0,373],[169489,0,559],[170422,1,0],[170608,1,0],[170982,2,0],[171355,3,186],[171915,3,279],[172568,1,279],[172941,1,0],[173221,1,559],[173967,2,0],[174340,2,0]]},{"lengthInSteps":16,"bpm":161,"changeBPM":false,"mustHitSection":false,"typeOfSection":0,"sectionNotes":[[175087,3,0],[175273,3,0],[175460,3,0],[175646,3,0],[175833,3,0],[176393,2,466],[177046,2,93],[177326,2,93]]},{"lengthInSteps":16,"bpm":161,"changeBPM":false,"mustHitSection":true,"typeOfSection":0,"sectionNotes":[[177886,2,279],[178539,1,93],[178818,0,279],[179285,0,186],[179658,0,0],[179938,1,0],[180125,1,0],[180311,1,0]]},{"lengthInSteps":16,"bpm":161,"changeBPM":false,"mustHitSection":false,"typeOfSection":0,"sectionNotes":[[180964,2,186],[181431,2,0],[181524,2,559],[182457,1,0],[182644,1,186],[183017,1,186],[183390,2,0],[183670,2,5485]]},{"lengthInSteps":16,"bpm":161,"changeBPM":false,"mustHitSection":true,"typeOfSection":0,"sectionNotes":[[187215,3,0],[187402,3,0],[187588,3,186],[188241,3,1492],[189921,3,0],[190107,3,0],[190294,3,0]]},{"lengthInSteps":16,"bpm":161,"changeBPM":false,"mustHitSection":false,"typeOfSection":0,"sectionNotes":[[190480,2,186],[190947,1,0],[191040,1,0],[191227,1,186],[191787,0,0],[191880,0,0],[191973,0,279]]},{"lengthInSteps":16,"bpm":161,"changeBPM":false,"mustHitSection":true,"typeOfSection":0,"sectionNotes":[[192719,0,186],[193186,2,0],[193279,2,0],[193466,2,186],[193839,3,0],[193932,3,0],[194026,3,0],[194212,3,279]]},{"lengthInSteps":16,"bpm":161,"changeBPM":false,"mustHitSection":false,"typeOfSection":0,"sectionNotes":[[194679,1,0],[194865,1,0],[195052,1,93],[195238,0,0],[195332,0,0],[195425,0,0],[195612,0,373]]},{"lengthInSteps":16,"bpm":161,"changeBPM":false,"mustHitSection":true,"typeOfSection":0,"sectionNotes":[[196171,2,559],[196918,2,0],[197011,2,0],[197104,2,0],[197291,3,186],[197571,3,466]]}]}